{
  "todos": [
    {
      "id": 1,
      "title": "delectus",
      "text": "delectus aut autem",
      "priority": "low"
    },
    {
      "title": "quis",
      "text": "quis ut nam facilis et officia qui",
      "priority": "low",
      "id": 2
    },
    {
      "id": 3,
      "title": "fugiat",
      "text": "fugiat veniam minus",
      "priority": "medium"
    },
    {
      "id": 4,
      "title": "etum",
      "text": "et porro tempora",
      "priority": "low"
    },
    {
      "id": 5,
      "title": "laboriosam",
      "text": "laboriosam mollitia et enim quasi adipisci quia provident illum",
      "priority": "high"
    },
    {
      "id": 6,
      "title": "quisa",
      "text": "qui ullam ratione quibusdam voluptatem quia omnis",
      "priority": "medium"
    },
    {
      "id": 7,
      "title": "illo",
      "text": "illo expedita consequatur quia in",
      "priority": "low"
    },
    {
      "id": 8,
      "title": "quonim",
      "text": "quo adipisci enim quam ut ab",
      "priority": "high"
    },
    {
      "id": 9,
      "title": "molestiae",
      "text": "molestiae perspiciatis ipsa",
      "priority": "low"
    },
    {
      "id": 10,
      "title": "illotu",
      "text": "illo est ratione doloremque quia maiores aut",
      "priority": "high"
    },
    {
      "id": 11,
      "title": "vero",
      "text": "vero rerum temporibus dolor",
      "priority": "low"
    },
    {
      "id": 12,
      "title": "ipsa",
      "text": "ipsa repellendus fugit nisi",
      "priority": "low"
    },
    {
      "id": 13,
      "title": "doloremque",
      "text": "et doloremque nulla",
      "priority": "medium"
    },
    {
      "id": 14,
      "title": "repellendus",
      "text": "repellendus sunt dolores architecto voluptatum",
      "priority": "medium"
    },
    {
      "id": 15,
      "title": "voluptatum",
      "text": "ab voluptatum amet voluptas",
      "priority": "low"
    },
    {
      "id": 16,
      "title": "accusamus",
      "text": "accusamus eos facilis sint et aut voluptatem",
      "priority": "low"
    },
    {
      "id": 17,
      "title": "laboriosam",
      "text": "quo laboriosam deleniti aut qui",
      "priority": "low"
    },
    {
      "id": 18,
      "title": "dolorum",
      "text": "dolorum est consequatur ea mollitia in culpa",
      "priority": "low"
    },
    {
      "id": 19,
      "title": "molestiae",
      "text": "molestiae ipsa aut voluptatibus pariatur dolor nihil",
      "priority": "high"
    },
    {
      "id": 1701269990051,
      "title": "todo",
      "text": "text todo",
      "priority": "high"
    },
    {
      "id": 1701280242700,
      "title": "todo 2",
      "text": "text todo",
      "priority": "medium"
    },
    {
      "id": 1701280268343,
      "title": "todo 3",
      "text": "text todo",
      "priority": "medium"
    },
    {
      "id": 1701280279139,
      "title": "todo 4",
      "text": "text todo",
      "priority": "high"
    },
    {
      "id": 1701280296513,
      "title": "todo 5",
      "text": "text todo",
      "priority": "low"
    },
    {
      "id": 1701280309016,
      "title": "todo 6",
      "text": "text todo",
      "priority": "low"
    },
    {
      "id": 1701337779767,
      "title": "todo 7",
      "text": "text todo",
      "priority": "high"
    },
    {
      "id": 1701337799670,
      "title": "todo 8",
      "text": "text todo",
      "priority": "medium"
    },
    {
      "id": 1701337811293,
      "title": "todo 9",
      "text": "text todo",
      "priority": "low"
    },
    {
      "id": 1701337822549,
      "title": "todo 10",
      "text": "text todo",
      "priority": "low"
    },
    {
      "id": 1701337835036,
      "title": "todo 11",
      "text": "text todo",
      "priority": "low"
    },
    {
      "id": 1701337981130,
      "title": "todo 12",
      "text": "text todo",
      "priority": "low"
    },
    {
      "id": 1701338760424,
      "title": "todo 13",
      "text": "text todo",
      "priority": "medium"
    },
    {
      "id": 1701338772888,
      "title": "todo 14",
      "text": "text todo",
      "priority": "low"
    },
    {
      "id": 1701338782069,
      "title": "todo 15",
      "text": "text todo",
      "priority": "high"
    },
    {
      "id": 1701338793828,
      "title": "todo 16",
      "text": "text todo",
      "priority": "high"
    },
    {
      "id": 1701338806017,
      "title": "todo 17",
      "text": "text todo",
      "priority": "low"
    },
    {
      "title": "todo 18",
      "text": "text todo",
      "priority": "low",
      "id": 1701338816333
    }
  ]
}